{
  "title": "LSNL Dealer App REST Api",
  "version": "v1",
  "baseUri": "http://dealerapp.logic-dev-lsn-n.isaac.local:8080/rest/v1",
  "protocols": [
    "HTTP"
  ],
  "resources": [
    {
      "relativeUri": "/dealer",
      "methods": [
        {
          "responses": {
            "200": {
              "code": "200",
              "body": {
                "application/json": {
                  "name": "application/json",
                  "example": "{\n  \"id\": 13,\n  \"name\": \"C. Ardealer\",\n  \"address\": \"Straat 1\\n9999 AA Plaats\",\n  \"phone\": \"06-12345679\",\n  \"email\": \"c@ardealer.net\",\n  \"externalReference\": \"000020\",\n  \"dealerLicensePlates\": [\n    \"AA-BB-11\",\n    \"1-ABC-23\"\n  ]\n}\n"
                }
              }
            }
          },
          "protocols": [
            "HTTP"
          ],
          "method": "get",
          "__METADATA__": {
            "primitiveValuesMeta": {
              "protocols": {
                "calculated": true
              }
            }
          }
        },
        {
          "responses": {
            "200": {
              "code": "200",
              "body": {
                "application/json": {
                  "name": "application/json",
                  "example": "{\n  \"id\": 13,\n  \"name\": \"C. Ardealer\",\n  \"address\": \"Straat 1\\n9999 AA Plaats\",\n  \"phone\": \"06-12345679\",\n  \"email\": \"c@ardealer.net\",\n  \"externalReference\": \"000020\",\n  \"active\": true\n}\n"
                }
              }
            }
          },
          "body": {
            "application/json": {
              "name": "application/json",
              "example": "{\n  \"id\": 13,\n  \"name\": \"C. Ardealer\",\n  \"address\": \"Straat 1\\n9999 AA Plaats\",\n  \"phone\": \"06-12345679\",\n  \"email\": \"c@ardealer.net\",\n  \"externalReference\": \"000020\"\n}\n"
            }
          },
          "protocols": [
            "HTTP"
          ],
          "description": "id is verplicht. Als andere velden ontbreken, dan worden ze niet overschreven.\n",
          "method": "post",
          "__METADATA__": {
            "primitiveValuesMeta": {
              "protocols": {
                "calculated": true
              }
            }
          }
        }
      ],
      "resources": [
        {
          "relativeUri": "/login",
          "methods": [
            {
              "responses": {
                "200": {
                  "code": "200",
                  "body": {
                    "application/json": {
                      "name": "application/json",
                      "example": "{\n  \"status\": \"SUCCESS\",\n  \"sessionId\": \"xxxxx\",\n  \"rememberMeToken\": \"yyyyy\"\n}\n"
                    },
                    "application/json+failure-example": {
                      "name": "application/json+failure-example",
                      "example": "{\n  \"status\": \"FAILED\"\n}\n"
                    }
                  }
                }
              },
              "body": {
                "application/json": {
                  "name": "application/json",
                  "example": "{\n  \"username\": \"dealerx\",\n  \"password\": \"P@ssw0rd\",\n  \"deviceId\": \"6zZlCS9PLFAs/mBHEAHKXF0t\"\n}\n"
                }
              },
              "protocols": [
                "HTTP"
              ],
              "method": "post",
              "__METADATA__": {
                "primitiveValuesMeta": {
                  "protocols": {
                    "calculated": true
                  }
                }
              }
            }
          ],
          "displayName": "/login",
          "__METADATA__": {
            "primitiveValuesMeta": {
              "displayName": {
                "calculated": true
              }
            }
          },
          "relativeUriPathSegments": [
            "login"
          ]
        },
        {
          "relativeUri": "/renewLogin",
          "methods": [
            {
              "responses": {
                "200": {
                  "code": "200",
                  "body": {
                    "application/json": {
                      "name": "application/json",
                      "example": "{\n  \"status\": \"SUCCESS\",\n  \"sessionId\": \"xxxxx\",\n  \"rememberMeToken\": \"yyyyy\"\n}\n"
                    },
                    "application/json+failure-example": {
                      "name": "application/json+failure-example",
                      "example": "{\n  \"status\": \"FAILED\"\n}\n"
                    }
                  }
                }
              },
              "body": {
                "application/json": {
                  "name": "application/json",
                  "example": "{\n  \"token\": \"yyyy\"\n}\n"
                }
              },
              "protocols": [
                "HTTP"
              ],
              "method": "post",
              "__METADATA__": {
                "primitiveValuesMeta": {
                  "protocols": {
                    "calculated": true
                  }
                }
              }
            }
          ],
          "displayName": "/renewLogin",
          "__METADATA__": {
            "primitiveValuesMeta": {
              "displayName": {
                "calculated": true
              }
            }
          },
          "relativeUriPathSegments": [
            "renewLogin"
          ]
        },
        {
          "relativeUri": "/logout",
          "methods": [
            {
              "responses": {
                "204": {
                  "code": "204"
                }
              },
              "protocols": [
                "HTTP"
              ],
              "method": "post",
              "__METADATA__": {
                "primitiveValuesMeta": {
                  "protocols": {
                    "calculated": true
                  }
                }
              }
            }
          ],
          "displayName": "/logout",
          "__METADATA__": {
            "primitiveValuesMeta": {
              "displayName": {
                "calculated": true
              }
            }
          },
          "relativeUriPathSegments": [
            "logout"
          ]
        },
        {
          "relativeUri": "/changePassword",
          "methods": [
            {
              "responses": {
                "200": {
                  "code": "200",
                  "body": {
                    "application/json": {
                      "name": "application/json",
                      "example": "{\n  \"status\": \"SUCCESS\",\n  \"sessionId\": \"xxxxx\",\n  \"rememberMeToken\": \"yyyyy\"\n}\n"
                    },
                    "application/json+failure-example": {
                      "name": "application/json+failure-example",
                      "example": "{\n  \"status\": \"FAILED\"\n}\n"
                    }
                  }
                }
              },
              "body": {
                "application/json": {
                  "name": "application/json",
                  "example": "{\n  \"username\": \"dealerx\",\n  \"password\": \"P@ssw0rd\",\n  \"newPassword\": \"W@chtw00rd\",\n  \"deviceId\": \"6zZlCS9PLFAs/mBHEAHKXF0t\"\n}\n"
                }
              },
              "protocols": [
                "HTTP"
              ],
              "method": "post",
              "__METADATA__": {
                "primitiveValuesMeta": {
                  "protocols": {
                    "calculated": true
                  }
                }
              }
            }
          ],
          "displayName": "/changePassword",
          "__METADATA__": {
            "primitiveValuesMeta": {
              "displayName": {
                "calculated": true
              }
            }
          },
          "relativeUriPathSegments": [
            "changePassword"
          ]
        },
        {
          "relativeUri": "/testdrives",
          "methods": [
            {
              "responses": {
                "200": {
                  "code": "200",
                  "body": {
                    "application/json": {
                      "name": "application/json",
                      "example": "[\n  {\n    \"id\": 1,\n    \"customerName\": \"Hans de Vries\",\n    \"customerPhone\": \"06-12345678\",\n    \"customerEmail\": \"Hans@devries.nl\",\n    \"started\": \"2015-09-17 09:13\",\n    \"returned\": \"2015-09-17 09:48\",\n    \"duration\": 35,\n    \"licensePlate\": \"11-22-AA\",\n    \"licensePlateDealer\": \"12-ABC-3\",\n    \"customerDriversLicenseUploaded\": false\n  }\n]\n"
                    }
                  }
                }
              },
              "protocols": [
                "HTTP"
              ],
              "description": "Geeft de testritten van de afgelopen 30 dagen.",
              "method": "get",
              "__METADATA__": {
                "primitiveValuesMeta": {
                  "protocols": {
                    "calculated": true
                  }
                }
              }
            },
            {
              "responses": {
                "200": {
                  "code": "200",
                  "body": {
                    "application/json": {
                      "name": "application/json",
                      "example": "{\n  \"id\": 1,\n  \"customerName\": \"Hans de Vries\",\n  \"customerPhone\": \"06-12345678\",\n  \"customerEmail\": \"Hans@devries.nl\",\n  \"started\": \"2015-09-17 09:13\",\n  \"returned\": \"2015-09-17 09:48\",\n  \"duration\": 35,\n  \"licensePlate\": \"11-22-AA\",\n  \"licensePlateDealer\": \"12-ABC-3\",\n  \"customerDriversLicenseUploaded\": false\n}\n"
                    }
                  }
                }
              },
              "body": {
                "multipart/form-data": {
                  "name": "multipart/form-data",
                  "formParameters": {
                    "customerName": {
                      "name": "customerName",
                      "displayName": "customerName",
                      "type": "string",
                      "required": false,
                      "example": "Hans de Vries",
                      "repeat": false,
                      "__METADATA__": {
                        "primitiveValuesMeta": {
                          "displayName": {
                            "calculated": true
                          },
                          "type": {
                            "insertedAsDefault": true
                          },
                          "required": {
                            "insertedAsDefault": true
                          },
                          "repeat": {
                            "insertedAsDefault": true
                          }
                        }
                      }
                    },
                    "customerPhone": {
                      "name": "customerPhone",
                      "displayName": "customerPhone",
                      "type": "string",
                      "required": false,
                      "example": "06-12345678",
                      "repeat": false,
                      "__METADATA__": {
                        "primitiveValuesMeta": {
                          "displayName": {
                            "calculated": true
                          },
                          "type": {
                            "insertedAsDefault": true
                          },
                          "required": {
                            "insertedAsDefault": true
                          },
                          "repeat": {
                            "insertedAsDefault": true
                          }
                        }
                      }
                    },
                    "customerEmail": {
                      "name": "customerEmail",
                      "displayName": "customerEmail",
                      "type": "string",
                      "required": false,
                      "example": "hans@devries.nl",
                      "repeat": false,
                      "__METADATA__": {
                        "primitiveValuesMeta": {
                          "displayName": {
                            "calculated": true
                          },
                          "type": {
                            "insertedAsDefault": true
                          },
                          "required": {
                            "insertedAsDefault": true
                          },
                          "repeat": {
                            "insertedAsDefault": true
                          }
                        }
                      }
                    },
                    "customerDriversLicense": {
                      "name": "customerDriversLicense",
                      "displayName": "customerDriversLicense",
                      "type": "file",
                      "required": false,
                      "repeat": false,
                      "__METADATA__": {
                        "primitiveValuesMeta": {
                          "displayName": {
                            "calculated": true
                          },
                          "required": {
                            "insertedAsDefault": true
                          },
                          "repeat": {
                            "insertedAsDefault": true
                          }
                        }
                      }
                    },
                    "licensePlate": {
                      "name": "licensePlate",
                      "displayName": "licensePlate",
                      "type": "string",
                      "required": false,
                      "example": "11-22-AA",
                      "repeat": false,
                      "__METADATA__": {
                        "primitiveValuesMeta": {
                          "displayName": {
                            "calculated": true
                          },
                          "type": {
                            "insertedAsDefault": true
                          },
                          "required": {
                            "insertedAsDefault": true
                          },
                          "repeat": {
                            "insertedAsDefault": true
                          }
                        }
                      }
                    },
                    "licensePlateDealer": {
                      "name": "licensePlateDealer",
                      "displayName": "licensePlateDealer",
                      "type": "string",
                      "required": false,
                      "example": "12-ABC-3",
                      "repeat": false,
                      "__METADATA__": {
                        "primitiveValuesMeta": {
                          "displayName": {
                            "calculated": true
                          },
                          "type": {
                            "insertedAsDefault": true
                          },
                          "required": {
                            "insertedAsDefault": true
                          },
                          "repeat": {
                            "insertedAsDefault": true
                          }
                        }
                      }
                    },
                    "carImage": {
                      "name": "carImage",
                      "displayName": "carImage",
                      "type": "file",
                      "required": false,
                      "repeat": false,
                      "__METADATA__": {
                        "primitiveValuesMeta": {
                          "displayName": {
                            "calculated": true
                          },
                          "required": {
                            "insertedAsDefault": true
                          },
                          "repeat": {
                            "insertedAsDefault": true
                          }
                        }
                      }
                    }
                  }
                }
              },
              "protocols": [
                "HTTP"
              ],
              "method": "post",
              "__METADATA__": {
                "primitiveValuesMeta": {
                  "protocols": {
                    "calculated": true
                  }
                }
              }
            }
          ],
          "resources": [
            {
              "relativeUri": "/{testDriveId}",
              "uriParameters": {
                "testDriveId": {
                  "name": "testDriveId",
                  "displayName": "testDriveId",
                  "type": "string",
                  "required": true,
                  "repeat": false,
                  "__METADATA__": {
                    "calculated": true,
                    "primitiveValuesMeta": {
                      "displayName": {
                        "calculated": true
                      },
                      "type": {
                        "insertedAsDefault": true
                      },
                      "required": {
                        "insertedAsDefault": true
                      },
                      "repeat": {
                        "insertedAsDefault": true
                      }
                    }
                  }
                }
              },
              "methods": [
                {
                  "responses": {
                    "200": {
                      "code": "200",
                      "body": {
                        "application/json": {
                          "name": "application/json",
                          "example": "{\n  \"id\": 1,\n  \"customerName\": \"Hans de Vries\",\n  \"customerPhone\": \"06-12345678\",\n  \"customerEmail\": \"Hans@devries.nl\",\n  \"started\": \"2015-09-17 09:13\",\n  \"returned\": \"2015-09-17 09:48\",\n  \"duration\": 35,\n  \"licensePlate\": \"11-22-AA\",\n  \"licensePlateDealer\": \"12-ABC-3\"\n}\n"
                        }
                      }
                    }
                  },
                  "protocols": [
                    "HTTP"
                  ],
                  "method": "get",
                  "__METADATA__": {
                    "primitiveValuesMeta": {
                      "protocols": {
                        "calculated": true
                      }
                    }
                  }
                }
              ],
              "resources": [
                {
                  "relativeUri": "/return",
                  "methods": [
                    {
                      "responses": {
                        "200": {
                          "code": "200",
                          "body": {
                            "application/json": {
                              "name": "application/json",
                              "example": "{\n  \"id\": 1,\n  \"customerName\": \"Hans de Vries\",\n  \"customerPhone\": \"06-12345678\",\n  \"customerEmail\": \"Hans@devries.nl\",\n  \"started\": \"2015-09-17 09:13\",\n  \"returned\": \"2015-09-17 09:48\",\n  \"duration\": 35,\n  \"licensePlate\": \"11-22-AA\",\n  \"licensePlateDealer\": \"12-ABC-3\"\n}\n"
                            }
                          }
                        }
                      },
                      "protocols": [
                        "HTTP"
                      ],
                      "method": "post",
                      "__METADATA__": {
                        "primitiveValuesMeta": {
                          "protocols": {
                            "calculated": true
                          }
                        }
                      }
                    }
                  ],
                  "displayName": "/return",
                  "__METADATA__": {
                    "primitiveValuesMeta": {
                      "displayName": {
                        "calculated": true
                      }
                    }
                  },
                  "relativeUriPathSegments": [
                    "return"
                  ]
                },
                {
                  "relativeUri": "/car",
                  "methods": [
                    {
                      "responses": {
                        "200": {
                          "code": "200",
                          "body": {
                            "image/*": {
                              "name": "image/*"
                            }
                          },
                          "description": "De foto van de auto dat bij deze testrit geupload is."
                        }
                      },
                      "protocols": [
                        "HTTP"
                      ],
                      "queryParameters": {
                        "maxWidth": {
                          "name": "maxWidth",
                          "displayName": "maxWidth",
                          "type": "string",
                          "required": false,
                          "example": "100",
                          "repeat": false,
                          "__METADATA__": {
                            "primitiveValuesMeta": {
                              "displayName": {
                                "calculated": true
                              },
                              "type": {
                                "insertedAsDefault": true
                              },
                              "required": {
                                "insertedAsDefault": true
                              },
                              "repeat": {
                                "insertedAsDefault": true
                              }
                            }
                          }
                        },
                        "maxHeight": {
                          "name": "maxHeight",
                          "displayName": "maxHeight",
                          "type": "string",
                          "required": false,
                          "example": "120",
                          "repeat": false,
                          "__METADATA__": {
                            "primitiveValuesMeta": {
                              "displayName": {
                                "calculated": true
                              },
                              "type": {
                                "insertedAsDefault": true
                              },
                              "required": {
                                "insertedAsDefault": true
                              },
                              "repeat": {
                                "insertedAsDefault": true
                              }
                            }
                          }
                        },
                        "encoding": {
                          "name": "encoding",
                          "displayName": "encoding",
                          "type": "string",
                          "required": false,
                          "example": "base64",
                          "repeat": false,
                          "__METADATA__": {
                            "primitiveValuesMeta": {
                              "displayName": {
                                "calculated": true
                              },
                              "type": {
                                "insertedAsDefault": true
                              },
                              "required": {
                                "insertedAsDefault": true
                              },
                              "repeat": {
                                "insertedAsDefault": true
                              }
                            }
                          }
                        }
                      },
                      "description": "Alle parameters zijn optioneel. Als één van de parameters maxWidth of maxHeight niet wordt meegegeven of nul is, dan wordt hij geacht gelijk te zijn aan de andere. Als beide niet worden meegegeven of beide nul zijn, dan wordt het originele bestand teruggegeven.\nAls encoding gelijk is aan de string \"base64\", dan wordt het plaatje als base64 teruggestuurd. De Content-Type header van de response is dan (bijvoorbeeld) \"image/png;base64\", en het plaatje kan ingeladen worden in een image tag door src=\"data:\" + contentType + \",\" + base64data in te stellen.\n",
                      "method": "get",
                      "__METADATA__": {
                        "primitiveValuesMeta": {
                          "protocols": {
                            "calculated": true
                          }
                        }
                      }
                    }
                  ],
                  "displayName": "/car",
                  "__METADATA__": {
                    "primitiveValuesMeta": {
                      "displayName": {
                        "calculated": true
                      }
                    }
                  },
                  "relativeUriPathSegments": [
                    "car"
                  ]
                }
              ],
              "displayName": "/{testDriveId}",
              "__METADATA__": {
                "primitiveValuesMeta": {
                  "displayName": {
                    "calculated": true
                  }
                }
              },
              "relativeUriPathSegments": [
                "{testDriveId}"
              ]
            }
          ],
          "displayName": "/testdrives",
          "__METADATA__": {
            "primitiveValuesMeta": {
              "displayName": {
                "calculated": true
              }
            }
          },
          "relativeUriPathSegments": [
            "testdrives"
          ]
        },
        {
          "relativeUri": "/loans",
          "methods": [
            {
              "responses": {
                "200": {
                  "code": "200",
                  "body": {
                    "application/json": {
                      "name": "application/json",
                      "example": "[\n  {\n    \"id\": 1,\n    \"customerName\": \"Hans de Vries\",\n    \"licensePlate\": \"11-22-AA\",\n    \"status\": \"Akkoord\",\n    \"amountInCents\": 450000,\n    \"finalized\": false\n  }\n]\n"
                    }
                  }
                }
              },
              "protocols": [
                "HTTP"
              ],
              "method": "get",
              "__METADATA__": {
                "primitiveValuesMeta": {
                  "protocols": {
                    "calculated": true
                  }
                }
              }
            }
          ],
          "resources": [
            {
              "relativeUri": "/calculate",
              "methods": [
                {
                  "responses": {
                    "200": {
                      "code": "200",
                      "body": {
                        "application/json": {
                          "name": "application/json",
                          "example": "[\n  {\n    \"amountInCents\": \"150000\",\n    \"duration\": \"12\",\n    \"totalLoanCost\": 155491,\n    \"monthlyPayment\": 12958,\n    \"annualPercentRate\": 6900,\n    \"yearlyCostPercentage\": 6900\n  }\n]\n"
                        }
                      }
                    }
                  },
                  "protocols": [
                    "HTTP"
                  ],
                  "queryParameters": {
                    "amount": {
                      "name": "amount",
                      "displayName": "amount",
                      "type": "integer",
                      "required": false,
                      "example": "150000",
                      "repeat": false,
                      "__METADATA__": {
                        "primitiveValuesMeta": {
                          "displayName": {
                            "calculated": true
                          },
                          "required": {
                            "insertedAsDefault": true
                          },
                          "repeat": {
                            "insertedAsDefault": true
                          }
                        }
                      }
                    }
                  },
                  "method": "get",
                  "__METADATA__": {
                    "primitiveValuesMeta": {
                      "protocols": {
                        "calculated": true
                      }
                    }
                  }
                }
              ],
              "displayName": "/calculate",
              "__METADATA__": {
                "primitiveValuesMeta": {
                  "displayName": {
                    "calculated": true
                  }
                }
              },
              "relativeUriPathSegments": [
                "calculate"
              ]
            },
            {
              "relativeUri": "/calculatorConfig",
              "methods": [
                {
                  "responses": {
                    "200": {
                      "code": "200",
                      "body": {
                        "application/json": {
                          "name": "application/json",
                          "example": "{\n  \"minAmountInCents\": 100000,\n  \"maxAmountInCents\": 2000000,\n  \"granularityInCents\": 100,\n  \"initialQuote\": [\n    {\n      \"amountInCents\": \"150000\",\n      \"duration\": \"12\",\n      \"totalLoanCost\": 155491,\n      \"monthlyPayment\": 12958,\n      \"annualPercentRate\": 6900,\n      \"yearlyCostPercentage\": 6900\n    }\n  ]\n}\n"
                        }
                      }
                    }
                  },
                  "protocols": [
                    "HTTP"
                  ],
                  "method": "get",
                  "__METADATA__": {
                    "primitiveValuesMeta": {
                      "protocols": {
                        "calculated": true
                      }
                    }
                  }
                }
              ],
              "displayName": "/calculatorConfig",
              "__METADATA__": {
                "primitiveValuesMeta": {
                  "displayName": {
                    "calculated": true
                  }
                }
              },
              "relativeUriPathSegments": [
                "calculatorConfig"
              ]
            },
            {
              "relativeUri": "/{loanId}",
              "uriParameters": {
                "loanId": {
                  "name": "loanId",
                  "displayName": "loanId",
                  "type": "string",
                  "required": true,
                  "repeat": false,
                  "__METADATA__": {
                    "calculated": true,
                    "primitiveValuesMeta": {
                      "displayName": {
                        "calculated": true
                      },
                      "type": {
                        "insertedAsDefault": true
                      },
                      "required": {
                        "insertedAsDefault": true
                      },
                      "repeat": {
                        "insertedAsDefault": true
                      }
                    }
                  }
                }
              },
              "methods": [
                {
                  "responses": {
                    "200": {
                      "code": "200",
                      "body": {
                        "application/json": {
                          "name": "application/json",
                          "example": "{\n  \"id\": 1,\n  \"customerName\": \"Hans de Vries\",\n  \"licensePlate\": \"11-22-AA\",\n  \"status\": \"Akkoord\",\n  \"amountInCents\": 450000,\n  \"finalized\": false\n}\n"
                        }
                      }
                    }
                  },
                  "protocols": [
                    "HTTP"
                  ],
                  "method": "get",
                  "__METADATA__": {
                    "primitiveValuesMeta": {
                      "protocols": {
                        "calculated": true
                      }
                    }
                  }
                }
              ],
              "resources": [
                {
                  "relativeUri": "/finalizeWithOwnershipDocument",
                  "methods": [
                    {
                      "responses": {
                        "204": {
                          "code": "204"
                        }
                      },
                      "body": {
                        "multipart/form-data": {
                          "name": "multipart/form-data",
                          "formParameters": {
                            "ownershipDocument": {
                              "name": "ownershipDocument",
                              "displayName": "ownershipDocument",
                              "type": "file",
                              "required": false,
                              "repeat": false,
                              "description": "image upload",
                              "__METADATA__": {
                                "primitiveValuesMeta": {
                                  "displayName": {
                                    "calculated": true
                                  },
                                  "required": {
                                    "insertedAsDefault": true
                                  },
                                  "repeat": {
                                    "insertedAsDefault": true
                                  }
                                }
                              }
                            }
                          }
                        }
                      },
                      "protocols": [
                        "HTTP"
                      ],
                      "description": "timeSlotDate en timeSlotLabel zijn slechts verplicht als contactMoment == LATER.\n",
                      "method": "post",
                      "__METADATA__": {
                        "primitiveValuesMeta": {
                          "protocols": {
                            "calculated": true
                          }
                        }
                      }
                    }
                  ],
                  "displayName": "/finalizeWithOwnershipDocument",
                  "__METADATA__": {
                    "primitiveValuesMeta": {
                      "displayName": {
                        "calculated": true
                      }
                    }
                  },
                  "relativeUriPathSegments": [
                    "finalizeWithOwnershipDocument"
                  ]
                }
              ],
              "displayName": "/{loanId}",
              "__METADATA__": {
                "primitiveValuesMeta": {
                  "displayName": {
                    "calculated": true
                  }
                }
              },
              "relativeUriPathSegments": [
                "{loanId}"
              ]
            }
          ],
          "displayName": "/loans",
          "__METADATA__": {
            "primitiveValuesMeta": {
              "displayName": {
                "calculated": true
              }
            }
          },
          "relativeUriPathSegments": [
            "loans"
          ]
        },
        {
          "relativeUri": "/contact",
          "methods": [
            {
              "responses": {
                "204": {
                  "code": "204"
                }
              },
              "body": {
                "multipart/form-data": {
                  "name": "multipart/form-data",
                  "formParameters": {
                    "customerName": {
                      "name": "customerName",
                      "displayName": "customerName",
                      "type": "string",
                      "required": false,
                      "example": "Hans de Vries",
                      "repeat": false,
                      "__METADATA__": {
                        "primitiveValuesMeta": {
                          "displayName": {
                            "calculated": true
                          },
                          "type": {
                            "insertedAsDefault": true
                          },
                          "required": {
                            "insertedAsDefault": true
                          },
                          "repeat": {
                            "insertedAsDefault": true
                          }
                        }
                      }
                    },
                    "customerPhone": {
                      "name": "customerPhone",
                      "displayName": "customerPhone",
                      "type": "string",
                      "required": false,
                      "example": "06-12345678",
                      "repeat": false,
                      "__METADATA__": {
                        "primitiveValuesMeta": {
                          "displayName": {
                            "calculated": true
                          },
                          "type": {
                            "insertedAsDefault": true
                          },
                          "required": {
                            "insertedAsDefault": true
                          },
                          "repeat": {
                            "insertedAsDefault": true
                          }
                        }
                      }
                    },
                    "customerEmail": {
                      "name": "customerEmail",
                      "displayName": "customerEmail",
                      "type": "string",
                      "required": false,
                      "example": "hans@devries.nl",
                      "repeat": false,
                      "__METADATA__": {
                        "primitiveValuesMeta": {
                          "displayName": {
                            "calculated": true
                          },
                          "type": {
                            "insertedAsDefault": true
                          },
                          "required": {
                            "insertedAsDefault": true
                          },
                          "repeat": {
                            "insertedAsDefault": true
                          }
                        }
                      }
                    },
                    "customerDriversLicense": {
                      "name": "customerDriversLicense",
                      "displayName": "customerDriversLicense",
                      "type": "file",
                      "required": false,
                      "repeat": false,
                      "description": "image upload",
                      "__METADATA__": {
                        "primitiveValuesMeta": {
                          "displayName": {
                            "calculated": true
                          },
                          "required": {
                            "insertedAsDefault": true
                          },
                          "repeat": {
                            "insertedAsDefault": true
                          }
                        }
                      }
                    },
                    "testDriveId": {
                      "name": "testDriveId",
                      "displayName": "testDriveId",
                      "type": "string",
                      "required": false,
                      "example": "124",
                      "repeat": false,
                      "__METADATA__": {
                        "primitiveValuesMeta": {
                          "displayName": {
                            "calculated": true
                          },
                          "type": {
                            "insertedAsDefault": true
                          },
                          "required": {
                            "insertedAsDefault": true
                          },
                          "repeat": {
                            "insertedAsDefault": true
                          }
                        }
                      }
                    },
                    "contactMoment": {
                      "name": "contactMoment",
                      "displayName": "contactMoment",
                      "type": "string",
                      "required": false,
                      "example": "NOW / LATER",
                      "repeat": false,
                      "__METADATA__": {
                        "primitiveValuesMeta": {
                          "displayName": {
                            "calculated": true
                          },
                          "type": {
                            "insertedAsDefault": true
                          },
                          "required": {
                            "insertedAsDefault": true
                          },
                          "repeat": {
                            "insertedAsDefault": true
                          }
                        }
                      }
                    },
                    "timeSlotDate": {
                      "name": "timeSlotDate",
                      "displayName": "timeSlotDate",
                      "type": "string",
                      "required": false,
                      "example": "2015-11-24",
                      "repeat": false,
                      "__METADATA__": {
                        "primitiveValuesMeta": {
                          "displayName": {
                            "calculated": true
                          },
                          "type": {
                            "insertedAsDefault": true
                          },
                          "required": {
                            "insertedAsDefault": true
                          },
                          "repeat": {
                            "insertedAsDefault": true
                          }
                        }
                      }
                    },
                    "timeSlotLabel": {
                      "name": "timeSlotLabel",
                      "displayName": "timeSlotLabel",
                      "type": "string",
                      "required": false,
                      "example": "middag",
                      "repeat": false,
                      "__METADATA__": {
                        "primitiveValuesMeta": {
                          "displayName": {
                            "calculated": true
                          },
                          "type": {
                            "insertedAsDefault": true
                          },
                          "required": {
                            "insertedAsDefault": true
                          },
                          "repeat": {
                            "insertedAsDefault": true
                          }
                        }
                      }
                    }
                  }
                }
              },
              "protocols": [
                "HTTP"
              ],
              "description": "timeSlotDate en timeSlotLabel zijn slechts verplicht als contactMoment == LATER.\n",
              "method": "post",
              "__METADATA__": {
                "primitiveValuesMeta": {
                  "protocols": {
                    "calculated": true
                  }
                }
              }
            }
          ],
          "resources": [
            {
              "relativeUri": "/schedule",
              "methods": [
                {
                  "responses": {
                    "200": {
                      "code": "200",
                      "body": {
                        "application/json": {
                          "name": "application/json",
                          "example": "{\n  \"canContactNow\" : true,\n  \"days\" : [ {\n    \"date\" : \"2016-01-22\",\n    \"slots\" : [ \"middag\", \"avond\" ]\n  }, {\n    \"date\" : \"2016-01-25\",\n    \"slots\" : [ \"ochtend\", \"middag\", \"avond\" ]\n  }, {\n    \"date\" : \"2016-01-26\",\n    \"slots\" : [ \"ochtend\", \"middag\", \"avond\" ]\n  }, {\n    \"date\" : \"2016-01-27\",\n    \"slots\" : [ \"ochtend\", \"middag\", \"avond\" ]\n  }, {\n    \"date\" : \"2016-01-28\",\n    \"slots\" : [ \"ochtend\", \"middag\", \"avond\" ]\n  } ]\n}\n"
                        }
                      }
                    }
                  },
                  "protocols": [
                    "HTTP"
                  ],
                  "description": "Contact schedule for the next 5 working days\n",
                  "method": "get",
                  "__METADATA__": {
                    "primitiveValuesMeta": {
                      "protocols": {
                        "calculated": true
                      }
                    }
                  }
                }
              ],
              "displayName": "/schedule",
              "__METADATA__": {
                "primitiveValuesMeta": {
                  "displayName": {
                    "calculated": true
                  }
                }
              },
              "relativeUriPathSegments": [
                "schedule"
              ]
            }
          ],
          "displayName": "/contact",
          "__METADATA__": {
            "primitiveValuesMeta": {
              "displayName": {
                "calculated": true
              }
            }
          },
          "relativeUriPathSegments": [
            "contact"
          ]
        },
        {
          "relativeUri": "/info",
          "methods": [
            {
              "responses": {
                "204": {
                  "code": "204"
                }
              },
              "body": {
                "application/json": {
                  "name": "application/json",
                  "example": "{\n  \"customerEmail\": \"hans@devries.nl\",\n  \"customerName\": \"Hans de Vries\",\n  \"amount\": 150000,\n  \"terms\": 12\n}\n"
                }
              },
              "protocols": [
                "HTTP"
              ],
              "description": "required: customerEmail and customerName\noptional: amount and duration (both should be either null or non-null)\n",
              "method": "post",
              "__METADATA__": {
                "primitiveValuesMeta": {
                  "protocols": {
                    "calculated": true
                  }
                }
              }
            }
          ],
          "displayName": "/info",
          "__METADATA__": {
            "primitiveValuesMeta": {
              "displayName": {
                "calculated": true
              }
            }
          },
          "relativeUriPathSegments": [
            "info"
          ]
        }
      ],
      "displayName": "/dealer",
      "__METADATA__": {
        "primitiveValuesMeta": {
          "displayName": {
            "calculated": true
          }
        }
      },
      "relativeUriPathSegments": [
        "dealer"
      ]
    },
    {
      "relativeUri": "/admin",
      "resources": [
        {
          "relativeUri": "/login",
          "methods": [
            {
              "responses": {
                "200": {
                  "code": "200",
                  "body": {
                    "application/json": {
                      "name": "application/json",
                      "example": "{\n  \"status\": \"SUCCESS\",\n  \"sessionId\": \"xxxxxxxxx\"\n}\n"
                    },
                    "application/json+failure-example": {
                      "name": "application/json+failure-example",
                      "example": "{\n  \"status\": \"FAILED\"\n}\n"
                    }
                  }
                }
              },
              "body": {
                "application/json": {
                  "name": "application/json",
                  "example": "{\n  \"username\": \"isaac\",\n  \"password\": \"p@ssw0rd\"\n}\n"
                }
              },
              "protocols": [
                "HTTP"
              ],
              "description": "Login for an admin\n",
              "method": "post",
              "__METADATA__": {
                "primitiveValuesMeta": {
                  "protocols": {
                    "calculated": true
                  }
                }
              }
            }
          ],
          "displayName": "/login",
          "__METADATA__": {
            "primitiveValuesMeta": {
              "displayName": {
                "calculated": true
              }
            }
          },
          "relativeUriPathSegments": [
            "login"
          ]
        },
        {
          "relativeUri": "/logout",
          "methods": [
            {
              "responses": {
                "204": {
                  "code": "204"
                }
              },
              "protocols": [
                "HTTP"
              ],
              "description": "Logout for an admin.\n",
              "method": "post",
              "__METADATA__": {
                "primitiveValuesMeta": {
                  "protocols": {
                    "calculated": true
                  }
                }
              }
            }
          ],
          "displayName": "/logout",
          "__METADATA__": {
            "primitiveValuesMeta": {
              "displayName": {
                "calculated": true
              }
            }
          },
          "relativeUriPathSegments": [
            "logout"
          ]
        },
        {
          "relativeUri": "/dealers",
          "methods": [
            {
              "responses": {
                "200": {
                  "code": "200",
                  "body": {
                    "application/json": {
                      "name": "application/json",
                      "example": "[\n  {\n    \"id\": 13,\n    \"name\": \"C. Ardealer\",\n    \"address\": \"Straat 1\\n9999 AA Plaats\",\n    \"phone\": \"06-12345679\",\n    \"email\": \"c@ardealer.net\",\n    \"externalReference\": \"000020\",\n    \"active\": true\n  }\n]\n"
                    }
                  }
                }
              },
              "protocols": [
                "HTTP"
              ],
              "description": "Get a list of dealers\nSessie authenticatie\n",
              "method": "get",
              "__METADATA__": {
                "primitiveValuesMeta": {
                  "protocols": {
                    "calculated": true
                  }
                }
              }
            },
            {
              "responses": {
                "200": {
                  "code": "200",
                  "body": {
                    "application/json": {
                      "name": "application/json",
                      "example": "{ \"id\": 13,\n  \"name\": \"C. Ardealer\",\n  \"address\": \"Straat 1\\n9999 AA Plaats\",\n  \"phone\": \"06-12345679\",\n  \"email\": \"c@ardealer.net\",\n  \"externalReference\": \"000020\",\n  \"active\": true\n}\n"
                    }
                  }
                }
              },
              "body": {
                "application/json": {
                  "name": "application/json",
                  "example": "{\n  \"id\": null,\n  \"name\": \"C. Ardealer\",\n  \"address\": \"Straat 1\\n9999 AA Plaats\",\n  \"phone\": \"06-12345679\",\n  \"email\": \"c@ardealer.net\",\n  \"password\": \"testpassword\",\n  \"externalReference\": \"000020\",\n  \"active\": true\n}\n"
                }
              },
              "protocols": [
                "HTTP"
              ],
              "description": "Als id niet null is, wordt een bestaand record geupdated, anders wordt een nieuw record aangemaakt.\nAls password niet null is, dan wordt het password geupdated, anders blijft het hetzelfde.\n\nMaximum lengtes van de strings:\n- name: 100\n- address: 255\n- email: 255\n- phone: 50\n- externalReference: 50\n",
              "method": "post",
              "__METADATA__": {
                "primitiveValuesMeta": {
                  "protocols": {
                    "calculated": true
                  }
                }
              }
            }
          ],
          "displayName": "/dealers",
          "__METADATA__": {
            "primitiveValuesMeta": {
              "displayName": {
                "calculated": true
              }
            }
          },
          "relativeUriPathSegments": [
            "dealers"
          ]
        },
        {
          "relativeUri": "/configuration/contactschedule",
          "methods": [
            {
              "responses": {
                "200": {
                  "code": "200",
                  "body": {
                    "text/plain": {
                      "name": "text/plain",
                      "example": "{\n  \"maxDays\": 5,\n  \"schedule\":\n  { \"monday\":\n    [ { \"label\": \"ochtend\", \"from\": \"09:00\", \"to\": \"12:00\" },\n      { \"label\": \"middag\", \"from\": \"12:30\", \"to\": \"16:00\" },\n      { \"label\": \"avond\", \"from\": \"17:00\", \"to\": \"20:00\" } ],\n    \"tuesday\":\n    [ { \"label\": \"ochtend\", \"from\": \"09:00\", \"to\": \"12:00\" },\n      { \"label\": \"middag\", \"from\": \"12:30\", \"to\": \"16:00\" },\n      { \"label\": \"avond\", \"from\": \"17:00\", \"to\": \"20:00\" } ],\n    \"wednesday\":\n    [ { \"label\": \"ochtend\", \"from\": \"09:00\", \"to\": \"12:00\" },\n      { \"label\": \"middag\", \"from\": \"12:30\", \"to\": \"16:00\" },\n      { \"label\": \"avond\", \"from\": \"17:00\", \"to\": \"20:00\" } ],\n    \"thursday\":\n    [ { \"label\": \"ochtend\", \"from\": \"09:00\", \"to\": \"12:00\" },\n      { \"label\": \"middag\", \"from\": \"12:30\", \"to\": \"16:00\" },\n      { \"label\": \"avond\", \"from\": \"17:00\", \"to\": \"20:00\" } ],\n    \"friday\":\n    [ { \"label\": \"ochtend\", \"from\": \"09:00\", \"to\": \"12:00\" },\n      { \"label\": \"middag\", \"from\": \"12:30\", \"to\": \"16:00\" },\n      { \"label\": \"avond\", \"from\": \"17:00\", \"to\": \"20:00\" } ],\n    \"saturday\": [ ],\n    \"sunday\": [ ]\n  },\n  \"exceptions\":\n  { \"2015-12-24\":\n    [ { \"label\": \"ochtend\", \"from\": \"09:00\", \"to\": \"12:00\" },\n      { \"label\": \"middag\", \"from\": \"12:30\", \"to\": \"16:00\" },\n      { \"label\": \"kerstavond\", \"from\": \"17:00\", \"to\": \"19:00\" } ],\n    \"2015-12-25\": [ ],\n    \"2015-12-31\":\n    [ { \"label\": \"ochtend\", \"from\": \"09:00\", \"to\": \"12:00\" } ]\n  }\n}\n"
                    }
                  }
                }
              },
              "protocols": [
                "HTTP"
              ],
              "method": "get",
              "__METADATA__": {
                "primitiveValuesMeta": {
                  "protocols": {
                    "calculated": true
                  }
                }
              }
            },
            {
              "responses": {
                "204": {
                  "code": "204"
                }
              },
              "body": {
                "text/plain": {
                  "name": "text/plain",
                  "example": "{\n  \"maxDays\": 5,\n  \"schedule\":\n  { \"monday\":\n    [ { \"label\": \"ochtend\", \"from\": \"09:00\", \"to\": \"12:00\" },\n      { \"label\": \"middag\", \"from\": \"12:30\", \"to\": \"16:00\" },\n      { \"label\": \"avond\", \"from\": \"17:00\", \"to\": \"20:00\" } ],\n    \"tuesday\":\n    [ { \"label\": \"ochtend\", \"from\": \"09:00\", \"to\": \"12:00\" },\n      { \"label\": \"middag\", \"from\": \"12:30\", \"to\": \"16:00\" },\n      { \"label\": \"avond\", \"from\": \"17:00\", \"to\": \"20:00\" } ],\n    \"wednesday\":\n    [ { \"label\": \"ochtend\", \"from\": \"09:00\", \"to\": \"12:00\" },\n      { \"label\": \"middag\", \"from\": \"12:30\", \"to\": \"16:00\" },\n      { \"label\": \"avond\", \"from\": \"17:00\", \"to\": \"20:00\" } ],\n    \"thursday\":\n    [ { \"label\": \"ochtend\", \"from\": \"09:00\", \"to\": \"12:00\" },\n      { \"label\": \"middag\", \"from\": \"12:30\", \"to\": \"16:00\" },\n      { \"label\": \"avond\", \"from\": \"17:00\", \"to\": \"20:00\" } ],\n    \"friday\":\n    [ { \"label\": \"ochtend\", \"from\": \"09:00\", \"to\": \"12:00\" },\n      { \"label\": \"middag\", \"from\": \"12:30\", \"to\": \"16:00\" },\n      { \"label\": \"avond\", \"from\": \"17:00\", \"to\": \"20:00\" } ],\n    \"saturday\": [ ],\n    \"sunday\": [ ]\n  },\n  \"exceptions\":\n  { \"2015-12-24\":\n    [ { \"label\": \"ochtend\", \"from\": \"09:00\", \"to\": \"12:00\" },\n      { \"label\": \"middag\", \"from\": \"12:30\", \"to\": \"16:00\" },\n      { \"label\": \"kerstavond\", \"from\": \"17:00\", \"to\": \"19:00\" } ],\n    \"2015-12-25\": [ ],\n    \"2015-12-31\":\n    [ { \"label\": \"ochtend\", \"from\": \"09:00\", \"to\": \"12:00\" } ]\n  }\n}\n"
                }
              },
              "protocols": [
                "HTTP"
              ],
              "method": "put",
              "__METADATA__": {
                "primitiveValuesMeta": {
                  "protocols": {
                    "calculated": true
                  }
                }
              }
            }
          ],
          "displayName": "/configuration/contactschedule",
          "__METADATA__": {
            "primitiveValuesMeta": {
              "displayName": {
                "calculated": true
              }
            }
          },
          "relativeUriPathSegments": [
            "configuration",
            "contactschedule"
          ]
        }
      ],
      "displayName": "/admin",
      "__METADATA__": {
        "primitiveValuesMeta": {
          "displayName": {
            "calculated": true
          }
        }
      },
      "relativeUriPathSegments": [
        "admin"
      ]
    },
    {
      "relativeUri": "/system",
      "resources": [
        {
          "relativeUri": "/checkStatus",
          "methods": [
            {
              "responses": {
                "200": {
                  "code": "200",
                  "body": {
                    "application/json": {
                      "name": "application/json",
                      "example": "{\n  \"middlewareStatus\" : \"OK\",\n  \"dialogueStatus\" : \"OK\",\n  \"databaseStatus\" : \"OK\"\n}\n"
                    }
                  }
                }
              },
              "protocols": [
                "HTTP"
              ],
              "description": "Query the current system status\n",
              "method": "get",
              "__METADATA__": {
                "primitiveValuesMeta": {
                  "protocols": {
                    "calculated": true
                  }
                }
              }
            }
          ],
          "displayName": "/checkStatus",
          "__METADATA__": {
            "primitiveValuesMeta": {
              "displayName": {
                "calculated": true
              }
            }
          },
          "relativeUriPathSegments": [
            "checkStatus"
          ]
        },
        {
          "relativeUri": "/loans",
          "methods": [
            {
              "responses": {
                "200": {
                  "code": "200",
                  "body": {
                    "application/json": {
                      "name": "application/json",
                      "example": "{\n  \"dealerReference\": \"apply\",\n  \"dealerLoanReference\": \"12345\",\n  \"testDriveId\": 124,\n  \"licensePlate\": \"AA-BB-11\",\n  \"name\": \"Hans de Vries\",\n  \"amount\": 150000,\n  \"status\": \"Goedgekeurd\",\n  \"finalized\": false\n}\n"
                    }
                  }
                }
              },
              "body": {
                "application/json": {
                  "name": "application/json",
                  "example": "{\n  \"dealerReference\": \"apply\",\n  \"dealerLoanReference\": \"12345\",\n  \"testDriveId\": 124,\n  \"name\": \"Hans de Vries\",\n  \"amount\": 150000,\n  \"status\": \"Goedgekeurd\"\n}\n"
                }
              },
              "protocols": [
                "HTTP"
              ],
              "description": "Used by Pangaea logic to update the dealerapp with the latest loan statusses.\n\nHet veld testDriveId mag null zijn als er geen koppeling gemaakt is. Als een niet-bestaand testDriveId wordt meegegeven, of een testDriveId dat niet gekoppeld is aan de gespecificeerde dealer, dan verschijnt er een warning in de log en wordt de lening niet gekoppeld (maar wel getoond aan de dealer).\n",
              "method": "post",
              "__METADATA__": {
                "primitiveValuesMeta": {
                  "protocols": {
                    "calculated": true
                  }
                }
              }
            }
          ],
          "displayName": "/loans",
          "__METADATA__": {
            "primitiveValuesMeta": {
              "displayName": {
                "calculated": true
              }
            }
          },
          "relativeUriPathSegments": [
            "loans"
          ]
        }
      ],
      "displayName": "/system",
      "__METADATA__": {
        "primitiveValuesMeta": {
          "displayName": {
            "calculated": true
          }
        }
      },
      "relativeUriPathSegments": [
        "system"
      ]
    }
  ],
  "__METADATA__": {
    "primitiveValuesMeta": {
      "protocols": {
        "calculated": true
      }
    }
  }
}